vjemmiemodels/__init__.py
vjemmiemodels/internal/__init__.py
vjemmiemodels/internal/gamingmoment.py
vjemmiemodels/internal/mediatype.py
vjemmiemodels/internal/pfm.py
vjemmiemodels/internal/reddit.py
vjemmiemodels/internal/skribbl.py
vjemmiemodels/internal/tidstyv.py
vjemmiemodels/public/__init__.py
vjemmiemodels/public/_gen_cls.py
vjemmiemodels-0.1.0.dist-info/WHEEL
vjemmiemodels-0.1.0.dist-info/METADATA
vjemmiemodels-0.1.0.dist-info/RECORD
